clearmatch/__init__.py
clearmatch/clearmatch.py
test/__init__.py
test/test.py
Clearmatch-1.0.0.dist-info/LICENSE
Clearmatch-1.0.0.dist-info/METADATA
Clearmatch-1.0.0.dist-info/WHEEL
Clearmatch-1.0.0.dist-info/top_level.txt
Clearmatch-1.0.0.dist-info/RECORD
