Metadata-Version: 2.1
Name: Clearmatch
Version: 1.0.0
Summary: Library for deterministic record matching
Home-page: https://github.com/dscolby/clearmatch
Author: Darren Colby
Author-email: dscolby17@gmail.com
License: UNKNOWN
Platform: UNKNOWN
Classifier: Programming Language :: Python :: 3
Classifier: License :: OSI Approved :: MIT License
Classifier: Operating System :: OS Independent
Requires-Dist: matplotlib
Requires-Dist: pandas
Requires-Dist: numpy
